kilroy_server_py_utils/__init__.py
kilroy_server_py_utils/categorizable.py
kilroy_server_py_utils/configurable.py
kilroy_server_py_utils/loadable.py
kilroy_server_py_utils/locks.py
kilroy_server_py_utils/observable.py
kilroy_server_py_utils/parameters/__init__.py
kilroy_server_py_utils/parameters/base.py
kilroy_server_py_utils/parameters/categorizable.py
kilroy_server_py_utils/parameters/nested.py
kilroy_server_py_utils/resources/__init__.py
kilroy_server_py_utils/savable.py
kilroy_server_py_utils/schema.py
kilroy_server_py_utils/utils.py
kilroy_server_py_utils-0.4.0.dist-info/LICENSE
kilroy_server_py_utils-0.4.0.dist-info/WHEEL
kilroy_server_py_utils-0.4.0.dist-info/METADATA
kilroy_server_py_utils-0.4.0.dist-info/RECORD
