Metadata-Version: 2.1
Name: kilroy-server-py-utils
Version: 0.4.0
Summary: utilities for kilroy servers in Python 🔧
Home-page: https://github.com/kilroybot/kilroy-server-py-utils
Author: kilroy
Author-email: kilroymail@pm.me
Requires-Python: >=3.10,<4.0
Classifier: License :: OSI Approved :: MIT License
Classifier: Operating System :: OS Independent
Classifier: Programming Language :: Python :: 3
Classifier: Programming Language :: Python :: 3.10
Requires-Dist: aiostream (>=0.4,<0.5)
Requires-Dist: fifolock (>=0.0,<0.1)
Requires-Dist: jsonschema (>=4.7,<5.0)
Requires-Dist: pydantic (>=1.9,<2.0)
Requires-Dist: pyhumps (>=3.7,<4.0)
Project-URL: Documentation, https://kilroybot.github.io/kilroy-server-py-utils
Project-URL: Repository, https://github.com/kilroybot/kilroy-server-py-utils
